setup.py
aquanToolbox.egg-info/PKG-INFO
aquanToolbox.egg-info/SOURCES.txt
aquanToolbox.egg-info/dependency_links.txt
aquanToolbox.egg-info/not-zip-safe
aquanToolbox.egg-info/requires.txt
aquanToolbox.egg-info/top_level.txt
pythonToolbox/__init__.py
pythonToolbox/dataloader.py
pythonToolbox/metrics.py
pythonToolbox/resultviewer.py
pythonToolbox/toolbox.py
pythonToolbox/version.py