Metadata-Version: 1.0
Name: aquanToolbox
Version: 1.0.0
Summary: The Auquan Toolbox for trading system development
Home-page: http://auquan.com/
Author: Auquan
Author-email: info@auquan.com
License: MIT
Platform: UNKNOWN
